sirmordred/__init__.py
sirmordred/_version.py
sirmordred/bin/sirmordred.py
sirmordred/config.py
sirmordred/error.py
sirmordred/github.py
sirmordred/sirmordred.py
sirmordred/task.py
sirmordred/task_autorefresh.py
sirmordred/task_collection.py
sirmordred/task_enrich.py
sirmordred/task_identities.py
sirmordred/task_manager.py
sirmordred/task_panels.py
sirmordred/task_projects.py
sirmordred/utils/find_affiliation_conflicts.py
sirmordred/utils/grimoirelab_valid.yml
sirmordred/utils/healthcheck.py
sirmordred/utils/logs/all.log
sirmordred/utils/micro.py
sirmordred/utils/panels_config.py
sirmordred/utils/projects.json
sirmordred/utils/projects_json2yml.py
sirmordred/utils/setup.cfg
sirmordred-1.2.6.dist-info/METADATA
sirmordred-1.2.6.dist-info/WHEEL
sirmordred-1.2.6.dist-info/entry_points.txt
sirmordred-1.2.6.dist-info/licenses/AUTHORS
sirmordred-1.2.6.dist-info/licenses/LICENSE
sirmordred-1.2.6.dist-info/RECORD
