Metadata-Version: 2.4
Name: sirmordred
Version: 1.2.6
Summary: Drive GrimoireLab tools to produce a dashboard
License: GPL-3.0+
License-File: AUTHORS
License-File: LICENSE
Keywords: development,grimoirelab
Author: GrimoireLab Developers
Requires-Python: >=3.10,<4.0
Classifier: Development Status :: 5 - Production/Stable
Classifier: Intended Audience :: Developers
Classifier: Intended Audience :: Science/Research
Classifier: License :: OSI Approved :: GNU General Public License v3 or later (GPLv3+)
Classifier: Programming Language :: Python :: 3
Classifier: Programming Language :: Python :: 3.10
Classifier: Programming Language :: Python :: 3.11
Classifier: Programming Language :: Python :: 3.12
Classifier: Programming Language :: Python :: 3.13
Classifier: Programming Language :: Python :: 3.14
Classifier: Topic :: Software Development
Requires-Dist: cereslib (>=0.3)
Requires-Dist: colorlog (>=6.4.1,<7.0.0)
Requires-Dist: file-read-backwards (>=3.1.0,<4.0.0)
Requires-Dist: graal (>=0.3)
Requires-Dist: grimoire-elk (>=0.102)
Requires-Dist: grimoirelab-panels (>=0.1)
Requires-Dist: grimoirelab-toolkit (>=0.3)
Requires-Dist: kidash (>=0.5)
Requires-Dist: opensearch-py (>=3.0.0,<4.0.0)
Requires-Dist: perceval (>=0.19)
Requires-Dist: perceval-mozilla (>=0.3)
Requires-Dist: perceval-opnfv (>=0.2)
Requires-Dist: perceval-puppet (>=0.2)
Requires-Dist: perceval-weblate (>=0.2)
Requires-Dist: sortinghat (>=0.7.20)
Project-URL: Bug Tracker, https://github.com/chaoss/grimoirelab-sirmordred/issues
Project-URL: Homepage, https://chaoss.github.io/grimoirelab/
Project-URL: Repository, https://github.com/chaoss/grimoirelab-sirmordred
